pixelink/__init__.py
pixelink/pixelink_api.py
pixelink/pixelink_cli.py
pixelink/pixelink_streamer.py
pixelink-1.4.0.dist-info/METADATA
pixelink-1.4.0.dist-info/RECORD
pixelink-1.4.0.dist-info/WHEEL
pixelink-1.4.0.dist-info/entry_points.txt
pixelink-1.4.0.dist-info/top_level.txt
