Metadata-Version: 2.1
Name: pixelink
Version: 1.4.0
Summary: A Python driver for the PixeLINK camera
Home-page: https://gitlab.com/hsmit/pixelink
Author: Hans Smit, Danny Smith
Author-email: jcsmit@xs4all.nl, danny.smith@uq.edu.au
License: MIT
Keywords: pixelink camera api driver
Platform: UNKNOWN
Classifier: Development Status :: 3 - Alpha
Classifier: Intended Audience :: Developers
Classifier: Topic :: Software Development :: Build Tools
Classifier: License :: OSI Approved :: MIT License
Classifier: Programming Language :: Python :: 2
Classifier: Programming Language :: Python :: 2.7
Classifier: Programming Language :: Python :: 3
Classifier: Programming Language :: Python :: 3.3
Classifier: Programming Language :: Python :: 3.4
Classifier: Programming Language :: Python :: 3.5
Classifier: Programming Language :: Python :: 3.6
Requires-Dist: decorator
